{
    "editions": [
        {
            "id": "01",
            "slug": "2026-05-07",
            "date": "07 de Maio, 2026",
            "title": "A Nova Era da Controladoria Inteligente",
            "summary": "Agentes de IA revolucionam o fechamento contábil e a análise financeira. Novas ferramentas de automação de dados e blockchain ganham tração no mercado."
        },
        {
            "id": "2052026",
            "slug": "2026-05-11",
            "date": "12 de maio de 2026",
            "title": "A Revolução da Transparência: IFRS 18 e a IA na Gestão de Caixa",
            "summary": "A nova norma IFRS 18 redefine a DRE para 2027, enquanto a IA consolida-se como pilar estratégico na tesouraria e automação de processos financeiros."
        }
    ]
}